stl/__init__.py
stl/cli.py
stl/core.py
stl/db.py
stl/spawn.py
stl/status.py
stl/time.py
stl/tests/__init__.py
stl/tests/test_cli.py
stl/tests/test_core.py
stl/tests/test_db.py
stl/tests/test_spawn.py
stl/tests/test_time.py
stltimelogger-0.0.4.dist-info/DESCRIPTION.rst
stltimelogger-0.0.4.dist-info/METADATA
stltimelogger-0.0.4.dist-info/RECORD
stltimelogger-0.0.4.dist-info/WHEEL
stltimelogger-0.0.4.dist-info/entry_points.txt
stltimelogger-0.0.4.dist-info/metadata.json
stltimelogger-0.0.4.dist-info/top_level.txt
