Metadata-Version: 2.0
Name: stltimelogger
Version: 0.0.4
Summary: cli time logger
Home-page: https://github.com/pavelsof/stl
Author: Pavel Sofroniev
Author-email: pavelsof@gmail.com
License: MIT
Keywords: cli time logger
Platform: UNKNOWN
Classifier: Development Status :: 4 - Beta
Classifier: Environment :: Console
Classifier: Intended Audience :: Developers
Classifier: License :: OSI Approved :: MIT License
Classifier: Programming Language :: Python :: 3
Classifier: Programming Language :: Python :: 3 :: Only
